sentinelvision/__init__.py
sentinelvision/run.py
sentinelvision/core/__init__.py
sentinelvision/core/config.py
sentinelvision/core/detector.py
sentinelvision/core/llm_module.py
sentinelvision/core/pipeline.py
sentinelvision/core/pose.py
sentinelvision/core/prompt_builder.py
sentinelvision/core/tracker.py
sentinelvision-0.1.0.dist-info/METADATA
sentinelvision-0.1.0.dist-info/WHEEL
sentinelvision-0.1.0.dist-info/entry_points.txt
sentinelvision-0.1.0.dist-info/top_level.txt
sentinelvision-0.1.0.dist-info/RECORD
