Metadata-Version: 2.4
Name: sentinelvision
Version: 0.1.0
Summary: Real-time autonomous visual tracking and reasoning system
Author: Your Name
License: MIT
Classifier: Programming Language :: Python :: 3
Classifier: License :: OSI Approved :: MIT License
Requires-Dist: ultralytics==8.0.172
Requires-Dist: mediapipe
Requires-Dist: opencv-python
Requires-Dist: numpy
Requires-Dist: torch
Requires-Dist: torchvision
Requires-Dist: scipy
Requires-Dist: matplotlib
Requires-Dist: onnxruntime
Requires-Dist: pyyaml
Dynamic: author
Dynamic: classifier
Dynamic: description
Dynamic: description-content-type
Dynamic: license
Dynamic: requires-dist
Dynamic: summary
